[
  {
    "text": "まず『ぼしゅう』『さんか』のどちらでゲームを始めるか選びましょう。",
    "image": "/images/rules/rule_1.png"
  },
  {
    "text": "募集者は『うさぎさん』『バイキンくん』のどちらかを選び『ぼしゅう』ボタンを押してください。",
    "image": "/images/rules/rule_2.png"
  },
  {
    "text": "表示されたワールドIDを参加者に共有したら、『はじめる』ボタンを押して待機しましょう。",
    "image": "/images/rules/rule_3.png"
  },
  {
    "text": "参加者は共有されたワールドIDを入力したら『はじめる』を押してください。ゲームの始まりをを待ちましょう。",
    "image": "/images/rules/rule_4.png"
  },
  {
    "text": "『うさぎさん』はおうちを目指して進みます。",
    "image": "/images/rules/rule_5.png"
  },
  {
    "text": "『ばいきんくん』は『うさぎさん』になんとか濃厚接触を試みます。",
    "image": "/images/rules/rule_6.png"
  },
  {
    "text": "それぞれのプレイヤーの移動は画面の下に表示される言葉を選択して行います。",
    "image": "/images/rules/rule_7.png"
  },
  {
    "text": "対象となる言葉と選択した言葉の関連性により移動方向が決まります。",
    "image": "/images/rules/rule_8.png"
  },
  {
    "text": "言葉の右側に出ているソナー(白い部分)でざっくりとどの方向に移動するかを知ることができます。",
    "image": "/images/rules/rule_9.png"
  },
  {
    "text": "『うさぎさん』は『ばいきんくん』とソーシャルディスタンスを保ちつつ、無事におうちにたどり着ければ勝利です。",
    "image": "/images/rules/rule_10.png"
  },
  {
    "text": "『ばいきんくん』は『うさぎさん』とのソーシャルディスタンスゾーン(赤いエリア)が重なると勝利です。",
    "image": "/images/rules/rule_11.png"
  }
]
